calculatesquareroottool/__init__.py
calculatesquareroottool/__main__.py
calculatesquareroottool-0.1.0.dist-info/METADATA
calculatesquareroottool-0.1.0.dist-info/WHEEL
calculatesquareroottool-0.1.0.dist-info/entry_points.txt
calculatesquareroottool-0.1.0.dist-info/top_level.txt
calculatesquareroottool-0.1.0.dist-info/RECORD
