Metadata-Version: 2.4
Name: calculatesquareroottool
Version: 0.1.0
Summary: A tool to calculate the square root of a number
Requires-Python: >=3.8
